LICENSE
MANIFEST.in
README.md
setup.py
allbasic/__init__.py
allbasic/admin.py
allbasic/apps.py
allbasic/domains.py
allbasic/helpers.py
allbasic/models.py
allbasic/presentations.py
allbasic/tests.py
allbasic/validations.py
allbasic/views.py
allbasic/migrations/__init__.py
django_allbasic.egg-info/PKG-INFO
django_allbasic.egg-info/SOURCES.txt
django_allbasic.egg-info/dependency_links.txt
django_allbasic.egg-info/top_level.txt