Metadata-Version: 2.1
Name: django-allbasic
Version: 0.1
Summary: All Basic is a simple Django app to to add some basic functionality to use the DRF API.
Home-page: https://www.adala.id/
Author: Yanwar Solahudin
Author-email: me@yanwarsolahudin.com
License: MIT License
Platform: UNKNOWN
Classifier: Environment :: Web Environment
Classifier: Framework :: Django
Classifier: Framework :: Django :: 2.0
Classifier: Intended Audience :: Developers
Classifier: License :: OSI Approved :: MIT License
Classifier: Operating System :: OS Independent
Classifier: Programming Language :: Python
Classifier: Programming Language :: Python :: 3.5
Classifier: Programming Language :: Python :: 3.6
Classifier: Topic :: Internet :: WWW/HTTP
Classifier: Topic :: Internet :: WWW/HTTP :: Dynamic Content
